{
  "groupName": "eng_contact_us",
  "urlPaths": [
    "/eng/contact_us_eng.php"
  ],
  "locales": {
    "en": {
      "urlPath": "/eng/contact_us_eng.php",
      "filePath": "eng/contact_us_eng.php",
      "locale": "en",
      "groupName": "eng_contact_us",
      "title": "www.glitter-tattoo.com",
      "description": "",
      "keywords": "",
      "headings": [
        "Contact Us"
      ],
      "bodyText": "Contact Us Your comments are important to us. If you have additional questions or comments, please do not hesitate to contact us. We shall be glad to assist you in the best possible manner: How to contact Us ? - Contact Form : Your Name: * Your E-Mail: * Contact number: * URL Address: Fax: Your Company: Country: Comments: February 22, 2026 - Address : Glitter-Tattoo 2220/11 , 36/1 Ramkhamhaeng Road, Huamark, Bangkapi, Bangkok 10240 Thailand Tel : (66) 0-2732-9870-1 Fax : (66) 0-2732-0879 Copyright www.glitter-tattoo.com 2220/11 Soi Ramkhamhaeng , 36/1 Ramkhamhaeng , Huamark, Bangkapi, Bangkok 10240 Thailand Tel. (66) 2732-9870-1 Fax. (66) 2732-0879",
      "bodyHtml": "<!-- InstanceBeginEditable name=\"EditRegion5\" --> \n\n<meta http-equiv=\"Content-Type\" content=\"text/html; charset=windows-874\">\n\n<!-- eng MENU -->\n\n<!--===============Credit www.apycom.com==========================--> \n<div id=\"copyright\"> <a href=\"http://apycom.com/\"> </a></div>\n\n<!-- InstanceEndEditable -->\n\n\n\n<p style=\"text-align:center; margin-left:auto; margin-right:auto;\">\n</p><table width=\"99%\" border=\"0\" cellspacing=\"0\" cellpadding=\"0\" style=\"text-align:center;\">\n\t<tbody><tr>\n\t<td style=\"width:47%; text-align:right;\"><a href=\"../thai/contact_us_thai.php\" target=\"_parent\"><img src=\"../flag/thai.png\" style=\"width:35px; height:30px; border:none;\"></a></td>\n\t<td style=\"width:6%; text-align:center;\"><a href=\"../eng/contact_us_eng.php\" target=\"_parent\"><img src=\"../flag/eng.png\" style=\"width:35px; height:30px; border:none;\"></a></td>\n\t<td style=\"width:47%; text-align:left;\"><a href=\"../ch/contact_us_ch.php\" target=\"_parent\"><img src=\"../flag/chn.png\" style=\"width:35px; height:30px; border:none;\"></a></td>\n\t</tr>\n </tbody></table>\n  <br>\n<p></p>\n\n\n<div id=\"art-main\">\n<div class=\"art-sheet\">\n            <div class=\"art-sheet-tl\"></div>\n            <div class=\"art-sheet-tr\"></div>\n            <div class=\"art-sheet-bl\"></div>\n            <div class=\"art-sheet-br\"></div>\n            <div class=\"art-sheet-tc\"></div>\n            <div class=\"art-sheet-bc\"></div>\n            <div class=\"art-sheet-cl\"></div>\n            <div class=\"art-sheet-cr\"></div>\n            <div class=\"art-sheet-cc\"></div>\n  <div class=\"art-sheet-body\">\n            \n            \n                <div class=\"art-header\">\n                    <div class=\"art-header-center\">\n                        <div class=\"art-header-png\"></div>\n                    </div>\n                  \n                    <div id=\"art-flash-area\">\n                    <div id=\"art-flash-container\" style=\"z-index:0;\">\n                    <object classid=\"clsid:D27CDB6E-AE6D-11cf-96B8-444553540000\" width=\"860\" height=\"215\" id=\"art-flash-object\" wmode=\"opaque\">\n                    \t<param name=\"movie\" value=\"../swf/head.swf\">\n                    \t<param name=\"quality\" value=\"high\">\n                    \t<param name=\"scale\" value=\"default\">\n                    \t<param name=\"wmode\" value=\"opaque\">\n                    \t<param name=\"flashvars\" value=\"color1=0xFFFFFF&amp;alpha1=.30&amp;framerate1=24&amp;loop=true&amp;wmode=transparent&amp;clip=../templates/images/flash.swf&amp;radius=3&amp;clipx=-7&amp;clipy=0&amp;initalclipw=900&amp;initalcliph=225&amp;clipw=870&amp;cliph=215&amp;width=870&amp;height=210&amp;textblock_width=0&amp;textblock_align=no\">\n                        <param name=\"swfliveconnect\" value=\"true\">\n                    \t<!--[if !IE]>-->\n                    \t<object type=\"application/x-shockwave-flash\" data=\"../swf/head.swf\" width=\"870\" height=\"215\" wmode=\"opaque\">\n                    \t    <param name=\"quality\" value=\"high\">\n                    \t    <param name=\"scale\" value=\"default\">\n                    \t    <param name=\"wmode\" value=\"opaque\">\n                        \t<param name=\"flashvars\" value=\"color1=0xFFFFFF&amp;alpha1=.30&amp;framerate1=24&amp;loop=true&amp;wmode=transparent&amp;clip=../templates/images/flash.swf&amp;radius=3&amp;clipx=-7&amp;clipy=0&amp;initalclipw=900&amp;initalcliph=225&amp;clipw=870&amp;cliph=220&amp;width=860&amp;height=215&amp;textblock_width=0&amp;textblock_align=no\">\n                            <param name=\"swfliveconnect\" value=\"true\">\n                    \t<!--<![endif]-->\n                    \t<!--<div class=\"art-flash-alt\"><a href=\"http://www.adobe.com/go/getflashplayer\"><img src=\"http://www.adobe.com/images/shared/download_buttons/get_flash_player.gif\" alt=\"Get Adobe Flash player\" /></a></div>-->\n                    \t<!--[if !IE]>-->\n                    \t</object>\n                    \t<!--<![endif]-->\n                    </object>\n                    \n                    </div>\n                    </div>\n                  \n                    <div class=\"art-logo\">\n                     <h1 id=\"name-text\" class=\"art-logo-name\"></h1>\n                     <h2 id=\"slogan-text\" class=\"art-logo-text\"></h2>\n                    </div>\n                </div>\n                \n                <div class=\"art-content-layout\">\n                    <div class=\"art-content-layout-row\">\n                        <div class=\"art-layout-cell art-content\">\n                          <div class=\"art-post\">\n                              <div class=\"art-post-tl\"></div>\n                              <div class=\"art-post-tr\"></div>\n                              <div class=\"art-post-bl\"></div>\n                              <div class=\"art-post-br\"></div>\n                              <div class=\"art-post-tc\"></div>\n                              <div class=\"art-post-bc\"></div>\n                              <div class=\"art-post-cl\"></div>\n                              <div class=\"art-post-cr\"></div>\n                              <div class=\"art-post-cc\"></div>\n                              <div class=\"art-post-body\">\n                          <div class=\"art-post-inner art-article\">\n                                          <div class=\"art-postmetadataheader\">\n                                              <h2 class=\"art-postheader\">\n                                              <!--<img src=\"templates/images/star_icon.png\" width=\"20\" height=\"20\" alt=\"\" />-->\n\t\t\t\t\t\t\t\t\t\t\t  <img src=\"../templates/images/postheadericon.png\" width=\"21\" height=\"22\" alt=\"\">\n\t\t\t\t\t\t\t\t\t\t\t\n                                               Contact Us\n\t\t\t\t\t\t\t\t\t\t\t  </h2>\n                                              <div class=\"art-postheadericons art-metadata-icons\">\n                                              </div>\n                            </div>\n                                          <div class=\"art-postcontent\">\n\t\t\t\t\t\t\t\t\t\t  \n\n\n<!-- InstanceBeginEditable name=\"EditRegion4\" -->\n                                              \n<p>\n\n              </p><table width=\"99%\" border=\"0\" align=\"center\" cellpadding=\"10\" cellspacing=\"0\" class=\"front\">\n                <tbody><tr>\n                  <td align=\"left\" valign=\"top\" class=\"txt1\"><p class=\"t1\">\n                    Your  comments are important to us. If you have additional questions or comments,\n                    <br> please  do not hesitate to contact us.\n                    <br>\n                        We shall be glad to assist you in the best possible  manner:</p>\n                  <p class=\"t2\"><b> How to contact Us ?</b><br>\n                          <br>\n                          <strong>- C</strong><strong>ontact Form :&nbsp;</strong>&nbsp;&nbsp;</p>\n                    <table border=\"0\" cellpadding=\"0\" cellspacing=\"5\" width=\"100%\">\n                        <tbody><tr>\n                          <td><form action=\"result_form.php\" method=\"post\">\n                              <table align=\"left\">\n                                <tbody><tr>\n                                  <td width=\"112\" align=\"right\" class=\"t4-m12\"><b>Your Name:</b></td>\n                                  <td width=\"363\" align=\"left\"><input name=\"name\" size=\"30\" value=\"\">\n                                    <span class=\"t4-m12 style7\"> *</span></td>\n                                </tr>\n                                <tr>\n                                  <td align=\"right\" class=\"t4-m12\"><b>Your E-Mail:</b></td>\n                                  <td align=\"left\"><input name=\"email\" size=\"30\" value=\"\">\n                                    <span class=\"t4-m12 style7\">                                    *</span></td>\n                                </tr>\n                                <tr>\n                                  <td align=\"right\" class=\"t4-m12\"><b>Contact number:</b></td>\n                                  <td align=\"left\"><input name=\"tel\" id=\"tel\" value=\"\" size=\"30\">\n                                    <span class=\"t4-m12 style7\"> *</span></td>\n                                </tr>\n                                <tr>\n                                  <td align=\"right\" class=\"t4-m12\"><b>URL Address:</b></td>\n                                  <td align=\"left\"><input name=\"URL\" size=\"30\" value=\"http://\"></td>\n                                </tr>\n                                <tr>\n                                  <td align=\"right\" valign=\"top\" class=\"t4-m12\"><b>Fax:</b></td>\n                                  <td align=\"left\"><input name=\"fax\" id=\"fax\" value=\"\" size=\"30\"></td>\n                                </tr>\n                                <tr>\n                                  <td align=\"right\" valign=\"top\" class=\"t4-m12\"><b>Your Company:</b></td>\n                                  <td align=\"left\"><input name=\"company\" size=\"30\" value=\"\"></td>\n                                </tr>\n                                <tr>\n                                  <td align=\"right\" valign=\"top\" class=\"t4-m12\"><b>Country:</b></td>\n                                  <td align=\"left\"><input name=\"country\" size=\"30\" value=\"\" id=\"country\"></td>\n                                </tr>\n                                <tr>\n                                  <td align=\"right\" valign=\"top\" class=\"t4-m12\"><b>Comments:</b></td>\n                                  <td align=\"left\"><b>\n                                    <textarea name=\"Comments\" cols=\"50\" rows=\"10\" wrap=\"soft\"></textarea>\n                                  </b></td>\n                                </tr>\n                                <tr>\n                                  <td class=\"t4-m12\"></td>\n                                  <td><input name=\"submit\" type=\"submit\" value=\"Send\">\n                                      <input name=\"reset\" type=\"reset\" value=\"Reset\">                                  </td>\n                                </tr>\n                              </tbody></table>\n                            <input type=\"hidden\" name=\"ipadress\" value=\"\"><input type=\"hidden\" name=\"referer\" value=\"\">                          </form></td>\n                        </tr>\n                        <tr>\n                          <td height=\"18\" valign=\"center\"><center>\n                     <font color=\"#000066\"><b>\n                              February 22, 2026                              </b> </font>\n                          </center></td>\n                        </tr>\n                    </tbody></table>\n                    <p class=\"t2\"><strong>- Address \n                      : </strong><span class=\"text\"> </span> <span class=\"text\">&nbsp;</span><font color=\"#FF0066\"><strong>Glitter-Tattoo</strong></font><span class=\"t4-m12\"><br>\n&nbsp;&nbsp;&nbsp;&nbsp;&nbsp;&nbsp;&nbsp;&nbsp;</span><span class=\"text\"><span class=\"t4-m12\">2220/11 , 36/1 Ramkhamhaeng Road,  Huamark, Bangkapi, <br>\n&nbsp;&nbsp;&nbsp;&nbsp;&nbsp;&nbsp;&nbsp; Bangkok 10240 Thailand</span><br>\n                                    <span class=\"t4-m12\">&nbsp;&nbsp;&nbsp;&nbsp;&nbsp;&nbsp;&nbsp; Tel </span> : (66) 0-2732-9870-1 Fax : (66) 0-2732-0879<br>\n                                   <!-- <br />\n                                    &nbsp;&nbsp;&nbsp;&nbsp;<strong>Mini Studio :</strong> TAWANNA (beside The Mall Bangkapi) Zone Fashion Room: AE 207\n&nbsp;&nbsp;&nbsp;&nbsp;&nbsp;&nbsp;&nbsp;&nbsp;&nbsp;&nbsp;&nbsp;&nbsp;&nbsp;&nbsp;&nbsp;&nbsp;&nbsp;&nbsp; \n                              &nbsp; &nbsp;&nbsp;&nbsp;<a href=\"images/map_en_b.jpg\" target=\"_blank\"><img src=\"images/map_en_s.jpg\" width=\"310\" height=\"207\" border=\"0\" /></a></span><span class=\"text\"><br />-->\n                        </span></p>\n                        \n                    <table width=\"100%\" border=\"0\" align=\"center\" cellpadding=\"0\" cellspacing=\"0\">\n                      <tbody><tr>\n                        <td><img src=\"../images/map_s.jpg\" width=\"410\" height=\"307\" border=\"0\"></td>\n                      </tr>\n                    </tbody></table>\n \n                        \n                   <!-- <p class=\"t2\"><strong>-&nbsp;Distributor in China</strong></p>\n                    <p class=\"t2\">&nbsp;&nbsp;&nbsp;&nbsp;&nbsp;&nbsp;NO 1 of Si Yu Street, NO 400 of Industry Rd, Haizhu District, GuangZhou, China<br />\n                      &nbsp;&nbsp;&nbsp;&nbsp;&nbsp;&nbsp;Contact person: Ms. Zhang<br />\n                      &nbsp;&nbsp;&nbsp;&nbsp;&nbsp;&nbsp;Mobile: 13640787836<br />\n                      &nbsp;&nbsp;&nbsp;&nbsp;&nbsp;&nbsp;e-mai:&nbsp;thaispa@126.com                    </p>\n                    <p class=\"t2\"><strong>- Distributor in Hong Kong</strong></p>\n                    <p class=\"t2\">&nbsp;&nbsp;&nbsp;&nbsp;&nbsp;&nbsp;15/F, Radiocity, 505 Hennessy Road, Causeway Bay, Hong Kong</p>\n                    <p class=\"t2\">&nbsp;&nbsp;&nbsp;&nbsp;&nbsp;&nbsp;Contact Person: </p>\n                    <p class=\"t2\">&nbsp;&nbsp;&nbsp;&nbsp;&nbsp;&nbsp;Ms. Heidi Sung&nbsp;: 852-9188-6263<br />\n                      &nbsp;&nbsp;&nbsp;&nbsp;&nbsp;&nbsp;Ms. Maryann Yip&nbsp;: 852-9096-0515 </p>\n                    <p class=\"t2\">&nbsp;&nbsp;&nbsp;&nbsp;&nbsp;&nbsp;Fax :&nbsp;852-2836-7582<br />\n                      &nbsp;&nbsp;&nbsp;&nbsp;&nbsp;&nbsp;Email :&nbsp;soie.intl@gmail.com</p>\n                    <p class=\"t2\" dir=\"ltr\"><strong>- Distributor in Dubai, United Arab Emirates</strong></p>\n                    <p class=\"t2\" dir=\"ltr\">&nbsp;&nbsp;&nbsp;&nbsp;&nbsp;&nbsp;Momentum Beauty  Products</p>\n                    <p class=\"t2\" dir=\"ltr\">&nbsp;&nbsp;&nbsp;&nbsp;&nbsp;&nbsp;Office # M-4, Al Karama  Bldg.</p>\n                    <p class=\"t2\" dir=\"ltr\">&nbsp;&nbsp;&nbsp;&nbsp;&nbsp;&nbsp;Next to Post Office,  Zabeel.</p>\n                    <p class=\"t2\" dir=\"ltr\">&nbsp;&nbsp;&nbsp;&nbsp;&nbsp;&nbsp;P.O.Box 62424, Dubai ,   United Arab Emirates  </p>\n                    <p class=\"t2\" dir=\"ltr\">&nbsp;</p>\n<p class=\"t2\" dir=\"ltr\">&nbsp;&nbsp;&nbsp;&nbsp;&nbsp;&nbsp;Office Tel: +971 4  3343823</p>\n                    <p class=\"t2\" dir=\"ltr\">&nbsp;&nbsp;&nbsp;&nbsp;&nbsp;&nbsp;Office Fax: +971 4  3343824 </p>\n<p class=\"t2\" dir=\"ltr\">&nbsp;&nbsp;&nbsp;&nbsp;&nbsp;&nbsp;Showroom Tel: +971 4  3452248</p>\n                    <p class=\"t2\" dir=\"ltr\">&nbsp;&nbsp;&nbsp;&nbsp;&nbsp;&nbsp;Showroom Fax: +971 4  3452249</p>\n                    <p class=\"t2\"><br />\n                      <br />\n                    </p>\n                    <p class=\"t2\">&nbsp;</p>\n                    <p class=\"t2\">&nbsp;</p>\n                    <p class=\"t2\"><span class=\"text\">                              <br />\n                    </span></p>--></td>\n                </tr>\n              </tbody></table>\n\n\n<p></p>\n<!-- InstanceEndEditable -->\n\n\n\n</div>\n<div class=\"cleared\"></div>\n</div>\n<div class=\"cleared\"></div>\n</div>\n</div>\n<div class=\"cleared\"></div>\n</div>\n</div>\n</div>\n<div class=\"cleared\"></div>\n                \n                \n                \n                \n                \n<!--============== FOOTER Section----==============------>                \n<div class=\"art-footer\">\n<div class=\"art-footer-t\"></div>\n<div class=\"art-footer-l\"></div>\n<div class=\"art-footer-b\"></div>\n<div class=\"art-footer-r\"></div>\n<div class=\"art-footer-body\"><a href=\"#\" class=\"art-rss-tag-icon\" title=\"RSS\"></a>\n<div class=\"art-footer-text\">\n<p>\n\n<span class=\"t2 style6\">\n\t<strong>\n    <span class=\"style8\">\n    <br>\n \n      <a href=\"https://www.facebook.com/pages/glitter-tattoo/109904935727480?ref=hl\" target=\"_blank\">\n      <img src=\"../images/banner/facebook2.png\" style=\"width:150px; height:45px; border:none;\"></a>\n      \n      <a href=\"http://www.dermaprothailand.com\" target=\"_blank\">\n      <img src=\"../images/banner/dermapro.png\" style=\"width:150px; height:45px; border:none;\"></a>\n         \n      <a href=\"http://www.beauty-supplier.com\" target=\"_blank\">\n      <img src=\"../images/banner/beauty-supplier.png\" style=\"width:150px; height:45px; border:none;\"></a>\n      \n      \n      <a href=\"http://www.haircrystal.com/\" target=\"_blank\">\n      <img src=\"../images/banner/haircrystal.png\" style=\"width:150px; height:45px; border:none;\"></a>\n  \n \n \n     <br>\n      Copyright   www.glitter-tattoo.com</span>\n      </strong>\n      </span>\n      <br>\n      <span class=\"t3 style6\">2220/11 Soi Ramkhamhaeng , 36/1 Ramkhamhaeng , Huamark, Bangkapi, Bangkok 10240 Thailand<br>\n\t\tTel. (66) 2732-9870-1  Fax. (66) 2732-0879\n\t\t</span>\n        </p>\n\n\n<div class=\"cleared\"></div>\n</div>\n</div>\n<div class=\"cleared\"></div>\n</div>\n</div>\n<div class=\"cleared\"></div>\n</div>\n    \n\n\n</div>",
      "images": [
        {
          "src": "/flag/thai.png",
          "alt": ""
        },
        {
          "src": "/flag/eng.png",
          "alt": ""
        },
        {
          "src": "/flag/chn.png",
          "alt": ""
        },
        {
          "src": "/templates/images/postheadericon.png",
          "alt": ""
        },
        {
          "src": "/images/map_s.jpg",
          "alt": ""
        },
        {
          "src": "/images/banner/facebook2.png",
          "alt": ""
        },
        {
          "src": "/images/banner/dermapro.png",
          "alt": ""
        },
        {
          "src": "/images/banner/beauty-supplier.png",
          "alt": ""
        },
        {
          "src": "/images/banner/haircrystal.png",
          "alt": ""
        }
      ]
    }
  },
  "canonicalPath": "/eng/contact_us_eng.php",
  "keywords": [],
  "images": [
    {
      "src": "/flag/thai.png",
      "alt": ""
    },
    {
      "src": "/flag/eng.png",
      "alt": ""
    },
    {
      "src": "/flag/chn.png",
      "alt": ""
    },
    {
      "src": "/templates/images/postheadericon.png",
      "alt": ""
    },
    {
      "src": "/images/map_s.jpg",
      "alt": ""
    },
    {
      "src": "/images/banner/facebook2.png",
      "alt": ""
    },
    {
      "src": "/images/banner/dermapro.png",
      "alt": ""
    },
    {
      "src": "/images/banner/beauty-supplier.png",
      "alt": ""
    },
    {
      "src": "/images/banner/haircrystal.png",
      "alt": ""
    }
  ]
}